eventlog/__init__.py
eventlog/admin.py
eventlog/apps.py
eventlog/datastructures.py
eventlog/events.py
eventlog/migrations/0001_initial.py
eventlog/migrations/0002_alter_event_group_alter_event_message_and_more.py
eventlog/migrations/0003_event_data.py
eventlog/migrations/0004_alter_event_group.py
eventlog/migrations/__init__.py
eventlog/models.py
eventlog/py.typed
eventlog/templates/admin/eventlog/event/change_form.html
eventlog/templates/admin/eventlog/event/change_list.html
eventlog/tests/__init__.py
eventlog/tests/test_eventlog.py
eventlog/tests/test_migrations.py
eventlog/tests/testapp/__init__.py
eventlog/tests/testapp/migrations/__init__.py
eventlog/tests/testapp/settings.py
eventlog/tests/testapp/urls.py
django_eventlog-2.2.2.dist-info/LICENSE
django_eventlog-2.2.2.dist-info/METADATA
django_eventlog-2.2.2.dist-info/WHEEL
django_eventlog-2.2.2.dist-info/entry_points.txt
django_eventlog-2.2.2.dist-info/RECORD
