Metadata-Version: 2.1
Name: django-eventlog
Version: 2.2.2
Summary: django-eventlog stores event messages in a Django model.
Home-page: https://barttc.github.io/django-eventlog/
License: MIT
Keywords: django,logging,logger,events
Author: Martin Mahner
Author-email: martin@mahner.org
Requires-Python: >=3.8,<4.0
Classifier: Development Status :: 5 - Production/Stable
Classifier: Environment :: Web Environment
Classifier: Framework :: Django
Classifier: Intended Audience :: Developers
Classifier: License :: OSI Approved :: MIT License
Classifier: Operating System :: OS Independent
Classifier: Programming Language :: Python
Classifier: Programming Language :: Python :: 3
Classifier: Programming Language :: Python :: 3.8
Classifier: Programming Language :: Python :: 3.9
Classifier: Programming Language :: Python :: 3.10
Classifier: Programming Language :: Python :: 3.11
Classifier: Programming Language :: Python :: 3.12
Classifier: Programming Language :: Python :: 3.13
Requires-Dist: django (>=3.2)
Project-URL: Bugtracker, https://github.com/bartTC/django-eventlog/issues
Project-URL: Documentation, https://barttc.github.io/django-eventlog/
Project-URL: Source, https://github.com/bartTC/django-eventlog
